cronus/__init__.py
cronus/bayes.py
cronus/default.py
cronus/diagnostics.py
cronus/likelihood.py
cronus/mcmc.py
cronus/optimize.py
cronus/run.py
cronus/save.py
cronus/start.py
cronus_mcmc-1.0.1.dist-info/METADATA
cronus_mcmc-1.0.1.dist-info/WHEEL
cronus_mcmc-1.0.1.dist-info/entry_points.txt
cronus_mcmc-1.0.1.dist-info/top_level.txt
cronus_mcmc-1.0.1.dist-info/RECORD
