Metadata-Version: 2.1
Name: cronus-mcmc
Version: 1.0.1
Summary: cronus: MCMC + MPI MADE EASY
Home-page: https://github.com/minaskar/cronus
Author: Minas Karamanis
Author-email: minaskar@gmail.com
License: UNKNOWN
Platform: UNKNOWN
Classifier: Programming Language :: Python :: 3
Classifier: License :: OSI Approved :: GNU General Public License v3 (GPLv3)
Classifier: Operating System :: OS Independent
Classifier: Intended Audience :: Science/Research
Classifier: Topic :: Scientific/Engineering
Classifier: Topic :: Scientific/Engineering :: Mathematics
Requires-Python: >=3.6
Requires-Dist: numpy
Requires-Dist: scipy
Requires-Dist: mpi4py
Requires-Dist: zeus-mcmc
Requires-Dist: iminuit
Requires-Dist: ruamel.yaml
Requires-Dist: h5py
